envoy/abstract/command/__init__.py
envoy/abstract/command/command.py
envoy/abstract/command/decorators.py
envoy/abstract/command/py.typed
envoy.abstract.command-0.0.4.dist-info/METADATA
envoy.abstract.command-0.0.4.dist-info/WHEEL
envoy.abstract.command-0.0.4.dist-info/namespace_packages.txt
envoy.abstract.command-0.0.4.dist-info/top_level.txt
envoy.abstract.command-0.0.4.dist-info/RECORD
