Metadata-Version: 2.1
Name: envoy.abstract.command
Version: 0.0.4
Summary: "Abstract command definitions for Envoy proxy's CI"
Home-page: https://github.com/envoyproxy/pytooling/tree/main/envoy.abstract.command
Author: Ryan Northey
Author-email: ryan@synca.io
Maintainer: Ryan Northey
Maintainer-email: ryan@synca.io
License: Apache Software License 2.0
Platform: UNKNOWN
Requires-Dist: abstracts (>=0.0.12)
